Metadata-Version: 2.4
Name: frida-server-manger
Version: 0.4
Summary: A tool to manage frida-server on Android devices
Author-email: King Jem <qqqqivy@gmail.com>
License: MIT
Project-URL: Homepage, https://github.com/KingJem/frida-server-manger
Classifier: Programming Language :: Python :: 3
Classifier: License :: OSI Approved :: MIT License
Classifier: Operating System :: OS Independent
Requires-Python: >=3.6
License-File: LICENSE
Requires-Dist: typer>=0.9.0
Requires-Dist: rich>=13.0.0
Dynamic: license-file
